scriptconfig/__init__.py
scriptconfig/__main__.py
scriptconfig/_ubelt_repr_extension.py
scriptconfig/argparse_ext.py
scriptconfig/cli.py
scriptconfig/config.py
scriptconfig/dataconfig.py
scriptconfig/diagnostics.py
scriptconfig/dict_like.py
scriptconfig/file_like.py
scriptconfig/modal.py
scriptconfig/py.typed
scriptconfig/smartcast.py
scriptconfig/subconfig.py
scriptconfig/value.py
scriptconfig/_cli/__init__.py
scriptconfig/_cli/main.py
scriptconfig/_cli/template.py
scriptconfig/util/__init__.py
scriptconfig/util/util_class.py
scriptconfig/util/util_class.pyi
scriptconfig/util/util_exception.py
scriptconfig-0.9.0.dist-info/licenses/LICENSE
scriptconfig-0.9.0.dist-info/METADATA
scriptconfig-0.9.0.dist-info/WHEEL
scriptconfig-0.9.0.dist-info/entry_points.txt
scriptconfig-0.9.0.dist-info/top_level.txt
scriptconfig-0.9.0.dist-info/RECORD
