Metadata-Version: 2.4
Name: scriptconfig
Version: 0.9.0
Summary: Easy dict-based script configuration with CLI support
Home-page: https://gitlab.kitware.com/utils/scriptconfig
Author: Kitware Inc., Jon Crall
Author-email: kitware@kitware.com, jon.crall@kitware.com
License: Apache 2
Classifier: Development Status :: 4 - Beta
Classifier: Intended Audience :: Developers
Classifier: Topic :: Software Development :: Libraries :: Python Modules
Classifier: Topic :: Utilities
Classifier: License :: OSI Approved :: Apache Software License
Classifier: Programming Language :: Python :: 3.8
Classifier: Programming Language :: Python :: 3.9
Classifier: Programming Language :: Python :: 3.10
Classifier: Programming Language :: Python :: 3.11
Classifier: Programming Language :: Python :: 3.12
Classifier: Programming Language :: Python :: 3.13
Classifier: Programming Language :: Python :: 3.14
Requires-Python: >=3.8
License-File: LICENSE
Requires-Dist: ubelt>=1.3.6
Requires-Dist: PyYAML>=6.0.1; python_version < "4.0" and python_version >= "3.12"
Requires-Dist: PyYAML>=6.0; python_version < "3.12" and python_version >= "3.11"
Requires-Dist: PyYAML>=6.0; python_version < "3.11" and python_version >= "3.10"
Requires-Dist: PyYAML>=5.4.1; python_version < "3.10" and python_version >= "3.9"
Requires-Dist: PyYAML>=5.4.1; python_version < "3.9" and python_version >= "3.8"
Requires-Dist: PyYAML>=5.4.1; python_version < "3.8" and python_version >= "3.7"
Requires-Dist: PyYAML>=5.4.1; python_version < "3.7" and python_version >= "3.6"
Provides-Extra: all
Requires-Dist: ubelt>=1.3.6; extra == "all"
Requires-Dist: PyYAML>=6.0.1; (python_version < "4.0" and python_version >= "3.12") and extra == "all"
Requires-Dist: PyYAML>=6.0; (python_version < "3.12" and python_version >= "3.11") and extra == "all"
Requires-Dist: PyYAML>=6.0; (python_version < "3.11" and python_version >= "3.10") and extra == "all"
Requires-Dist: PyYAML>=5.4.1; (python_version < "3.10" and python_version >= "3.9") and extra == "all"
Requires-Dist: PyYAML>=5.4.1; (python_version < "3.9" and python_version >= "3.8") and extra == "all"
Requires-Dist: PyYAML>=5.4.1; (python_version < "3.8" and python_version >= "3.7") and extra == "all"
Requires-Dist: PyYAML>=5.4.1; (python_version < "3.7" and python_version >= "3.6") and extra == "all"
Requires-Dist: pytest>=8.1.1; (python_version < "4.0" and python_version >= "3.13") and extra == "all"
Requires-Dist: pytest>=8.1.1; (python_version < "3.13" and python_version >= "3.12") and extra == "all"
Requires-Dist: pytest>=8.1.1; (python_version < "3.12" and python_version >= "3.11") and extra == "all"
Requires-Dist: pytest>=6.2.5; (python_version < "3.11" and python_version >= "3.10") and extra == "all"
Requires-Dist: pytest>=6.2.5; (python_version < "3.10" and python_version >= "3.8") and extra == "all"
Requires-Dist: coverage>=6.1.1; python_version >= "3.10" and extra == "all"
Requires-Dist: coverage>=5.3.1; (python_version < "3.10" and python_version >= "3.9") and extra == "all"
Requires-Dist: coverage>=6.1.1; (python_version < "3.9" and python_version >= "3.8") and extra == "all"
Requires-Dist: pytest-cov; extra == "all"
Requires-Dist: xdoctest>=1.1.5; extra == "all"
Requires-Dist: numpy>=2.1.0; (python_version < "4.0" and python_version >= "3.13") and extra == "all"
Requires-Dist: numpy>=1.26.0; (python_version < "3.13" and python_version >= "3.12") and extra == "all"
Requires-Dist: numpy>=1.23.2; (python_version < "3.12" and python_version >= "3.11") and extra == "all"
Requires-Dist: numpy>=1.21.6; (python_version < "3.11" and python_version >= "3.10") and extra == "all"
Requires-Dist: numpy>=1.19.3; (python_version < "3.10" and python_version >= "3.9") and extra == "all"
Requires-Dist: numpy>=1.19.2; (python_version < "3.9" and python_version >= "3.8") and extra == "all"
Requires-Dist: numpy>=1.14.5; (python_version < "3.8" and python_version >= "3.7") and extra == "all"
Requires-Dist: numpy>=1.12.0; (python_version < "3.7" and python_version >= "3.6") and extra == "all"
Requires-Dist: numpy>=1.11.1; (python_version < "3.6" and python_version >= "3.5") and extra == "all"
Requires-Dist: numpy>=1.11.1; (python_version < "3.5" and python_version >= "3.4") and extra == "all"
Requires-Dist: numpy>=1.11.1; (python_version < "3.4" and python_version >= "2.7") and extra == "all"
Requires-Dist: omegaconf>=2.2.2; python_version >= "3.6" and extra == "all"
Requires-Dist: rich_argparse>=1.1.0; python_version >= "3.7" and extra == "all"
Requires-Dist: argcomplete>=3.0.5; extra == "all"
Provides-Extra: runtime
Requires-Dist: ubelt>=1.3.6; extra == "runtime"
Requires-Dist: PyYAML>=6.0.1; (python_version < "4.0" and python_version >= "3.12") and extra == "runtime"
Requires-Dist: PyYAML>=6.0; (python_version < "3.12" and python_version >= "3.11") and extra == "runtime"
Requires-Dist: PyYAML>=6.0; (python_version < "3.11" and python_version >= "3.10") and extra == "runtime"
Requires-Dist: PyYAML>=5.4.1; (python_version < "3.10" and python_version >= "3.9") and extra == "runtime"
Requires-Dist: PyYAML>=5.4.1; (python_version < "3.9" and python_version >= "3.8") and extra == "runtime"
Requires-Dist: PyYAML>=5.4.1; (python_version < "3.8" and python_version >= "3.7") and extra == "runtime"
Requires-Dist: PyYAML>=5.4.1; (python_version < "3.7" and python_version >= "3.6") and extra == "runtime"
Provides-Extra: tests
Requires-Dist: pytest>=8.1.1; (python_version < "4.0" and python_version >= "3.13") and extra == "tests"
Requires-Dist: pytest>=8.1.1; (python_version < "3.13" and python_version >= "3.12") and extra == "tests"
Requires-Dist: pytest>=8.1.1; (python_version < "3.12" and python_version >= "3.11") and extra == "tests"
Requires-Dist: pytest>=6.2.5; (python_version < "3.11" and python_version >= "3.10") and extra == "tests"
Requires-Dist: pytest>=6.2.5; (python_version < "3.10" and python_version >= "3.8") and extra == "tests"
Requires-Dist: coverage>=6.1.1; python_version >= "3.10" and extra == "tests"
Requires-Dist: coverage>=5.3.1; (python_version < "3.10" and python_version >= "3.9") and extra == "tests"
Requires-Dist: coverage>=6.1.1; (python_version < "3.9" and python_version >= "3.8") and extra == "tests"
Requires-Dist: pytest-cov; extra == "tests"
Requires-Dist: xdoctest>=1.1.5; extra == "tests"
Provides-Extra: optional
Requires-Dist: numpy>=2.1.0; (python_version < "4.0" and python_version >= "3.13") and extra == "optional"
Requires-Dist: numpy>=1.26.0; (python_version < "3.13" and python_version >= "3.12") and extra == "optional"
Requires-Dist: numpy>=1.23.2; (python_version < "3.12" and python_version >= "3.11") and extra == "optional"
Requires-Dist: numpy>=1.21.6; (python_version < "3.11" and python_version >= "3.10") and extra == "optional"
Requires-Dist: numpy>=1.19.3; (python_version < "3.10" and python_version >= "3.9") and extra == "optional"
Requires-Dist: numpy>=1.19.2; (python_version < "3.9" and python_version >= "3.8") and extra == "optional"
Requires-Dist: numpy>=1.14.5; (python_version < "3.8" and python_version >= "3.7") and extra == "optional"
Requires-Dist: numpy>=1.12.0; (python_version < "3.7" and python_version >= "3.6") and extra == "optional"
Requires-Dist: numpy>=1.11.1; (python_version < "3.6" and python_version >= "3.5") and extra == "optional"
Requires-Dist: numpy>=1.11.1; (python_version < "3.5" and python_version >= "3.4") and extra == "optional"
Requires-Dist: numpy>=1.11.1; (python_version < "3.4" and python_version >= "2.7") and extra == "optional"
Requires-Dist: omegaconf>=2.2.2; python_version >= "3.6" and extra == "optional"
Requires-Dist: rich_argparse>=1.1.0; python_version >= "3.7" and extra == "optional"
Requires-Dist: argcomplete>=3.0.5; extra == "optional"
Provides-Extra: docs
Requires-Dist: sphinx>=5.0.1; extra == "docs"
Requires-Dist: sphinx-autobuild>=2021.3.14; extra == "docs"
Requires-Dist: sphinx_rtd_theme>=1.0.0; extra == "docs"
Requires-Dist: sphinxcontrib-napoleon>=0.7; extra == "docs"
Requires-Dist: sphinx-autoapi>=1.8.4; extra == "docs"
Requires-Dist: Pygments>=2.9.0; extra == "docs"
Requires-Dist: myst_parser>=0.18.0; extra == "docs"
Requires-Dist: sphinx-reredirects>=0.0.1; extra == "docs"
Provides-Extra: linting
Requires-Dist: flake8>=5.0.0; extra == "linting"
Provides-Extra: all-strict
Requires-Dist: ubelt==1.3.6; extra == "all-strict"
Requires-Dist: PyYAML==6.0.1; (python_version < "4.0" and python_version >= "3.12") and extra == "all-strict"
Requires-Dist: PyYAML==6.0; (python_version < "3.12" and python_version >= "3.11") and extra == "all-strict"
Requires-Dist: PyYAML==6.0; (python_version < "3.11" and python_version >= "3.10") and extra == "all-strict"
Requires-Dist: PyYAML==5.4.1; (python_version < "3.10" and python_version >= "3.9") and extra == "all-strict"
Requires-Dist: PyYAML==5.4.1; (python_version < "3.9" and python_version >= "3.8") and extra == "all-strict"
Requires-Dist: PyYAML==5.4.1; (python_version < "3.8" and python_version >= "3.7") and extra == "all-strict"
Requires-Dist: PyYAML==5.4.1; (python_version < "3.7" and python_version >= "3.6") and extra == "all-strict"
Requires-Dist: pytest==8.1.1; (python_version < "4.0" and python_version >= "3.13") and extra == "all-strict"
Requires-Dist: pytest==8.1.1; (python_version < "3.13" and python_version >= "3.12") and extra == "all-strict"
Requires-Dist: pytest==8.1.1; (python_version < "3.12" and python_version >= "3.11") and extra == "all-strict"
Requires-Dist: pytest==6.2.5; (python_version < "3.11" and python_version >= "3.10") and extra == "all-strict"
Requires-Dist: pytest==6.2.5; (python_version < "3.10" and python_version >= "3.8") and extra == "all-strict"
Requires-Dist: coverage==6.1.1; python_version >= "3.10" and extra == "all-strict"
Requires-Dist: coverage==5.3.1; (python_version < "3.10" and python_version >= "3.9") and extra == "all-strict"
Requires-Dist: coverage==6.1.1; (python_version < "3.9" and python_version >= "3.8") and extra == "all-strict"
Requires-Dist: pytest-cov; extra == "all-strict"
Requires-Dist: xdoctest==1.1.5; extra == "all-strict"
Requires-Dist: numpy==2.1.0; (python_version < "4.0" and python_version >= "3.13") and extra == "all-strict"
Requires-Dist: numpy==1.26.0; (python_version < "3.13" and python_version >= "3.12") and extra == "all-strict"
Requires-Dist: numpy==1.23.2; (python_version < "3.12" and python_version >= "3.11") and extra == "all-strict"
Requires-Dist: numpy==1.21.6; (python_version < "3.11" and python_version >= "3.10") and extra == "all-strict"
Requires-Dist: numpy==1.19.3; (python_version < "3.10" and python_version >= "3.9") and extra == "all-strict"
Requires-Dist: numpy==1.19.2; (python_version < "3.9" and python_version >= "3.8") and extra == "all-strict"
Requires-Dist: numpy==1.14.5; (python_version < "3.8" and python_version >= "3.7") and extra == "all-strict"
Requires-Dist: numpy==1.12.0; (python_version < "3.7" and python_version >= "3.6") and extra == "all-strict"
Requires-Dist: numpy==1.11.1; (python_version < "3.6" and python_version >= "3.5") and extra == "all-strict"
Requires-Dist: numpy==1.11.1; (python_version < "3.5" and python_version >= "3.4") and extra == "all-strict"
Requires-Dist: numpy==1.11.1; (python_version < "3.4" and python_version >= "2.7") and extra == "all-strict"
Requires-Dist: omegaconf==2.2.2; python_version >= "3.6" and extra == "all-strict"
Requires-Dist: rich_argparse==1.1.0; python_version >= "3.7" and extra == "all-strict"
Requires-Dist: argcomplete==3.0.5; extra == "all-strict"
Provides-Extra: runtime-strict
Requires-Dist: ubelt==1.3.6; extra == "runtime-strict"
Requires-Dist: PyYAML==6.0.1; (python_version < "4.0" and python_version >= "3.12") and extra == "runtime-strict"
Requires-Dist: PyYAML==6.0; (python_version < "3.12" and python_version >= "3.11") and extra == "runtime-strict"
Requires-Dist: PyYAML==6.0; (python_version < "3.11" and python_version >= "3.10") and extra == "runtime-strict"
Requires-Dist: PyYAML==5.4.1; (python_version < "3.10" and python_version >= "3.9") and extra == "runtime-strict"
Requires-Dist: PyYAML==5.4.1; (python_version < "3.9" and python_version >= "3.8") and extra == "runtime-strict"
Requires-Dist: PyYAML==5.4.1; (python_version < "3.8" and python_version >= "3.7") and extra == "runtime-strict"
Requires-Dist: PyYAML==5.4.1; (python_version < "3.7" and python_version >= "3.6") and extra == "runtime-strict"
Provides-Extra: tests-strict
Requires-Dist: pytest==8.1.1; (python_version < "4.0" and python_version >= "3.13") and extra == "tests-strict"
Requires-Dist: pytest==8.1.1; (python_version < "3.13" and python_version >= "3.12") and extra == "tests-strict"
Requires-Dist: pytest==8.1.1; (python_version < "3.12" and python_version >= "3.11") and extra == "tests-strict"
Requires-Dist: pytest==6.2.5; (python_version < "3.11" and python_version >= "3.10") and extra == "tests-strict"
Requires-Dist: pytest==6.2.5; (python_version < "3.10" and python_version >= "3.8") and extra == "tests-strict"
Requires-Dist: coverage==6.1.1; python_version >= "3.10" and extra == "tests-strict"
Requires-Dist: coverage==5.3.1; (python_version < "3.10" and python_version >= "3.9") and extra == "tests-strict"
Requires-Dist: coverage==6.1.1; (python_version < "3.9" and python_version >= "3.8") and extra == "tests-strict"
Requires-Dist: pytest-cov; extra == "tests-strict"
Requires-Dist: xdoctest==1.1.5; extra == "tests-strict"
Provides-Extra: optional-strict
Requires-Dist: numpy==2.1.0; (python_version < "4.0" and python_version >= "3.13") and extra == "optional-strict"
Requires-Dist: numpy==1.26.0; (python_version < "3.13" and python_version >= "3.12") and extra == "optional-strict"
Requires-Dist: numpy==1.23.2; (python_version < "3.12" and python_version >= "3.11") and extra == "optional-strict"
Requires-Dist: numpy==1.21.6; (python_version < "3.11" and python_version >= "3.10") and extra == "optional-strict"
Requires-Dist: numpy==1.19.3; (python_version < "3.10" and python_version >= "3.9") and extra == "optional-strict"
Requires-Dist: numpy==1.19.2; (python_version < "3.9" and python_version >= "3.8") and extra == "optional-strict"
Requires-Dist: numpy==1.14.5; (python_version < "3.8" and python_version >= "3.7") and extra == "optional-strict"
Requires-Dist: numpy==1.12.0; (python_version < "3.7" and python_version >= "3.6") and extra == "optional-strict"
Requires-Dist: numpy==1.11.1; (python_version < "3.6" and python_version >= "3.5") and extra == "optional-strict"
Requires-Dist: numpy==1.11.1; (python_version < "3.5" and python_version >= "3.4") and extra == "optional-strict"
Requires-Dist: numpy==1.11.1; (python_version < "3.4" and python_version >= "2.7") and extra == "optional-strict"
Requires-Dist: omegaconf==2.2.2; python_version >= "3.6" and extra == "optional-strict"
Requires-Dist: rich_argparse==1.1.0; python_version >= "3.7" and extra == "optional-strict"
Requires-Dist: argcomplete==3.0.5; extra == "optional-strict"
Provides-Extra: docs-strict
Requires-Dist: sphinx==5.0.1; extra == "docs-strict"
Requires-Dist: sphinx-autobuild==2021.3.14; extra == "docs-strict"
Requires-Dist: sphinx_rtd_theme==1.0.0; extra == "docs-strict"
Requires-Dist: sphinxcontrib-napoleon==0.7; extra == "docs-strict"
Requires-Dist: sphinx-autoapi==1.8.4; extra == "docs-strict"
Requires-Dist: Pygments==2.9.0; extra == "docs-strict"
Requires-Dist: myst_parser==0.18.0; extra == "docs-strict"
Requires-Dist: sphinx-reredirects==0.0.1; extra == "docs-strict"
Provides-Extra: linting-strict
Requires-Dist: flake8==5.0.0; extra == "linting-strict"
Dynamic: author
Dynamic: author-email
Dynamic: classifier
Dynamic: description
Dynamic: description-content-type
Dynamic: home-page
Dynamic: license
Dynamic: license-file
Dynamic: provides-extra
Dynamic: requires-dist
Dynamic: requires-python
Dynamic: summary
